{
  "bytes": 10077183,
  "dataset_id": "rw_ons_lms_v140",
  "inspection": {
    "kind": "openxml",
    "shared_strings": {
      "compressed_bytes": 120,
      "path": "xl/sharedStrings.xml",
      "present": true,
      "uncompressed_bytes": 137
    },
    "styles": {
      "compressed_bytes": 323,
      "path": "xl/styles.xml",
      "present": true,
      "uncompressed_bytes": 674
    },
    "workbook": {
      "path": "xl/workbook.xml",
      "present": true,
      "sheet_count_estimate": 1,
      "uncompressed_bytes_prefix": 347
    },
    "worksheet_dimensions": {
      "xl/worksheets/sheet1.xml": "A1"
    },
    "worksheets": [
      {
        "compressed_bytes": 10074194,
        "path": "xl/worksheets/sheet1.xml",
        "uncompressed_bytes": 125535079
      }
    ],
    "zip": {
      "entry_count": 9,
      "max_compression_ratio": 12.461054353330896,
      "max_compression_ratio_entry": "xl/worksheets/sheet1.xml",
      "max_entry_uncompressed_bytes": 125535079,
      "total_uncompressed_bytes": 125539052
    }
  },
  "path": "corpus_public/sha256_3c5e6db6a4ec1c7a22605c8733729b50ca1beba9f3bf1f4ac057459919f47ed9.xlsx",
  "sha256": "3c5e6db6a4ec1c7a22605c8733729b50ca1beba9f3bf1f4ac057459919f47ed9",
  "timestamp": "2026-02-08T16:47:58.994141+00:00"
}
